spesdebris/__init__.py
spesdebris/__main__.py
spesdebris/dbxhandler.py
spesdebris/extrq.py
spesdebris/fcmhandler.py
spesdebris/scheduling.py
spesdebris/server.py
spesdebris/settings-sample.ini
spesdebris-0.0.3.dist-info/METADATA
spesdebris-0.0.3.dist-info/WHEEL
spesdebris-0.0.3.dist-info/top_level.txt
spesdebris-0.0.3.dist-info/RECORD
