Metadata-Version: 2.1
Name: spesdebris
Version: 0.0.3
Summary: Python-based desktop automationand cross-device communication suite
Home-page: https://github.com/ABS96/spesdebris
Author: Benedek Solt Antók
Author-email: abs@abs.ezw.me
License: UNKNOWN
Platform: UNKNOWN
Classifier: Programming Language :: Python :: 3
Classifier: License :: OSI Approved :: GNU General Public License v3 (GPLv3)
Classifier: Operating System :: Microsoft :: Windows :: Windows 10
